examples/__init__.py
examples/async_usage.py
examples/basic_usage.py
examples/batch_operations.py
examples/complete_example.py
examples/error_handling.py
examples/langchain_integration.py
motionos/__init__.py
motionos/async_client.py
motionos/client.py
motionos/errors.py
motionos/security.py
motionos/types.py
motionos/utils.py
motionos/auth/__init__.py
motionos/auth/headers.py
motionos/auth/manager.py
motionos/auth/roles.py
motionos/config/__init__.py
motionos/config/decorators.py
motionos/config/defaults.py
motionos/config/environment.py
motionos/config/manager.py
motionos/config/validator.py
motionos/errors/__init__.py
motionos/errors/base.py
motionos/errors/categories.py
motionos/errors/factory.py
motionos/errors/handler.py
motionos/explain/__init__.py
motionos/explain/analyzer.py
motionos/explain/confidence.py
motionos/explain/formatter.py
motionos/ingestion/__init__.py
motionos/ingestion/builder.py
motionos/ingestion/validator.py
motionos/retrieval/__init__.py
motionos/retrieval/builder.py
motionos/retrieval/intent.py
motionos/retrieval/policy.py
motionos/retry/__init__.py
motionos/retry/executor.py
motionos/retry/strategy.py
motionos/runtime/__init__.py
motionos/runtime/adapters.py
motionos/runtime/detection.py
motionos/runtime/restrictions.py
motionos/security/__init__.py
motionos/security/audit.py
motionos/security/boundaries.py
motionos/security/validation.py
motionos/simulation/__init__.py
motionos/simulation/mock_client.py
motionos/simulation/scenarios.py
motionos/testing/__init__.py
motionos/testing/assertions.py
motionos/testing/fixtures.py
motionos/testing/mocks.py
motionos/timeline/__init__.py
motionos/timeline/client.py
motionos/timeline/walker.py
motionos/types/__init__.py
motionos/types/common.py
motionos/types/config.py
motionos/types/explanation.py
motionos/types/memory.py
motionos/types/retrieval.py
motionos/types/timeline.py
motionos/versioning/__init__.py
motionos/versioning/deprecation.py
motionos/versioning/features.py
motionos-2.0.0.dist-info/METADATA
motionos-2.0.0.dist-info/WHEEL
motionos-2.0.0.dist-info/top_level.txt
motionos-2.0.0.dist-info/RECORD
