Metadata-Version: 2.4
Name: motionos
Version: 2.0.0
Summary: Official Python SDK for MotionOS - Enterprise AI Memory & Context Management
Author-email: MotionOS <support@motionos.dev>
License: MIT
Project-URL: Homepage, https://motionos.dev
Project-URL: Documentation, https://docs.motionos.dev
Project-URL: Repository, https://github.com/motionos/sdk-python
Project-URL: Issues, https://github.com/motionos/sdk-python/issues
Project-URL: Changelog, https://github.com/motionos/sdk-python/blob/main/CHANGELOG.md
Keywords: ai,memory,agents,llm,context,semantic-search,motionos,rag,vector-search,langchain,llamaindex,crewai,enterprise,ai-memory
Classifier: Development Status :: 5 - Production/Stable
Classifier: Intended Audience :: Developers
Classifier: License :: OSI Approved :: MIT License
Classifier: Programming Language :: Python :: 3
Classifier: Programming Language :: Python :: 3.9
Classifier: Programming Language :: Python :: 3.10
Classifier: Programming Language :: Python :: 3.11
Classifier: Programming Language :: Python :: 3.12
Classifier: Programming Language :: Python :: 3.13
Classifier: Topic :: Software Development :: Libraries :: Python Modules
Classifier: Topic :: Scientific/Engineering :: Artificial Intelligence
Classifier: Typing :: Typed
Requires-Python: >=3.9
Requires-Dist: requests>=2.28.0
Requires-Dist: httpx>=0.24.0
Provides-Extra: dev
Requires-Dist: pytest>=7.0.0; extra == "dev"
Requires-Dist: pytest-asyncio>=0.21.0; extra == "dev"
Requires-Dist: pytest-cov>=4.0.0; extra == "dev"
Requires-Dist: responses>=0.23.0; extra == "dev"
Requires-Dist: respx>=0.20.0; extra == "dev"
Requires-Dist: black>=23.0.0; extra == "dev"
Requires-Dist: mypy>=1.0.0; extra == "dev"
Requires-Dist: ruff>=0.1.0; extra == "dev"
Provides-Extra: async
Requires-Dist: httpx>=0.24.0; extra == "async"
